graphextract/__init__.py
graphextract/svg_extractor.py
graphextract/transfo.py
graphextract/version.py
graphextract-1.3.0.dist-info/licenses/AUTHORS.rst
graphextract-1.3.0.dist-info/licenses/LICENSE
graphextract-1.3.0.dist-info/METADATA
graphextract-1.3.0.dist-info/WHEEL
graphextract-1.3.0.dist-info/top_level.txt
graphextract-1.3.0.dist-info/RECORD
